hectare/_HectareCHeaderGen.py
hectare/_HectareListener.py
hectare/_HectareVhdlGen.py
hectare/__init__.py
hectare/_hectare_types.py
hectare/_vhdl_templates.py
hectare/hectare.py
hectare-0.2.4.dist-info/LICENSE.txt
hectare-0.2.4.dist-info/METADATA
hectare-0.2.4.dist-info/WHEEL
hectare-0.2.4.dist-info/entry_points.txt
hectare-0.2.4.dist-info/top_level.txt
hectare-0.2.4.dist-info/RECORD
