Metadata-Version: 2.1
Name: hectare
Version: 0.2.4
Summary: VHDL generator from SystemRDL
Home-page: https://techlab.desy.de
Author: Jan Marjanovic (DESY)
Author-email: jan.marjanovic@desy.de
License: UNKNOWN
Keywords: systemrdl fpga vhdl axi registers
Platform: UNKNOWN
Classifier: Programming Language :: Python :: 3
Classifier: License :: OSI Approved :: BSD License
Classifier: Operating System :: OS Independent
Requires-Python: >=3.5
Requires-Dist: systemrdl-compiler (>=1.12.0)
